easygit_folder/__init__.py
easygit_folder/easygit.py
testrungit19-0.0.1.dist-info/LICENSE
testrungit19-0.0.1.dist-info/METADATA
testrungit19-0.0.1.dist-info/WHEEL
testrungit19-0.0.1.dist-info/top_level.txt
testrungit19-0.0.1.dist-info/RECORD
